setup.cfg
setup.py
koodous/__init__.py
koodous/cli.py
koodous/koodous.py
koodous/utils.py
koodous_py.egg-info/PKG-INFO
koodous_py.egg-info/SOURCES.txt
koodous_py.egg-info/dependency_links.txt
koodous_py.egg-info/entry_points.txt
koodous_py.egg-info/requires.txt
koodous_py.egg-info/top_level.txt