Metadata-Version: 1.1
Name: koodous-py
Version: 0.7
Summary: Module to interact with Koodous API
Home-page: https://koodous.com/
Author: Antonio Sanchez
Author-email: asanchez@koodous.com
License: Apache Version 2
Download-URL: https://github.com/Koodous/python-sdk/archive/master.zip
Keywords: koodous,api,sdk,python,android,apk,malware
Platform: UNKNOWN
